runsh/__init__.py
runsh/cli.py
runsh/config.py
runsh/constants.py
runsh/parser.py
runsh/commands/__init__.py
runsh/commands/cache_command.py
runsh/commands/config_command.py
runsh/commands/debug_command.py
runsh/commands/script_command.py
runsh/config/__init__.py
runsh/config/github.py
runsh/config/local.py
runsh/config/providers.py
runsh/utils/__init__.py
runsh/utils/script_processing.py
runsh-2.0.4.dist-info/licenses/LICENSE
runsh-2.0.4.dist-info/METADATA
runsh-2.0.4.dist-info/WHEEL
runsh-2.0.4.dist-info/entry_points.txt
runsh-2.0.4.dist-info/top_level.txt
runsh-2.0.4.dist-info/RECORD
