Metadata-Version: 2.4
Name: runsh
Version: 2.0.4
Summary: Transform your shell scripts into powerful CLI tools with autocomplete, help messages, and argument validation
Author-email: Sisung Kim <sisung.kim1@gmail.com>
Requires-Python: <4.0,>=3.10
License-File: LICENSE
Requires-Dist: cleo<3.0.0,>=2.1.0
Requires-Dist: PyYAML<7.0,>=6.0
Requires-Dist: requests<3.0.0,>=2.28.0
Dynamic: license-file
